cligraph/__init__.py
cligraph/core.py
cligraph/logger.py
cligraph-0.1.4.dist-info/licenses/LICENSE
cligraph-0.1.4.dist-info/METADATA
cligraph-0.1.4.dist-info/WHEEL
cligraph-0.1.4.dist-info/top_level.txt
cligraph-0.1.4.dist-info/RECORD
