Metadata-Version: 2.4
Name: cligraph
Version: 0.1.4
Summary: A package inspired by tqdm, that adds an updateable graph to the cli for tracking a value within a loop.
Author: Brayden Cloutier
License:                                  Apache License
Requires-Python: >=3.8
License-File: LICENSE
Requires-Dist: appdirs==1.4.4
Requires-Dist: logger
Dynamic: license-file
